lcyutils/__init__.py
lcyutils/emailMe/__init__.py
lcyutils/help/__init__.py
lcyutils/qqmessage/__init__.py
lcyutils-0.0.3.dist-info/LICENSE.txt
lcyutils-0.0.3.dist-info/METADATA
lcyutils-0.0.3.dist-info/WHEEL
lcyutils-0.0.3.dist-info/top_level.txt
lcyutils-0.0.3.dist-info/RECORD
