Metadata-Version: 2.1
Name: lcyutils
Version: 0.0.3
Summary: LCY Personal Tools
Home-page: https://github.com/lcy1317/lcytools
Author: luochengyu
Author-email: luochengyu1317@163.com
Maintainer: luochengyu
Maintainer-email: luochengyu1317@163.com
License: MIT License
Platform: all
Classifier: Programming Language :: Python :: 3
Classifier: License :: OSI Approved :: MIT License
Classifier: Operating System :: OS Independent
Requires-Python: >=3.6
License-File: LICENSE.txt
Requires-Dist: requests (>=2.26.0)
